plugin_viperlog_http/__init__.py
plugin_viperlog_http/http_processors.py
viperlog_http_plugin-0.2.102.dist-info/METADATA
viperlog_http_plugin-0.2.102.dist-info/WHEEL
viperlog_http_plugin-0.2.102.dist-info/top_level.txt
viperlog_http_plugin-0.2.102.dist-info/RECORD
